[{"roll":"67063","name":"KAVITA MANOJ BOGATTI"},{"roll":"67064","name":"MIDHAT IQBAL SHAIKH"},{"roll":"67065","name":"VALENCY  FERNANDES"},{"roll":"67066","name":"ASHTAN JOHN FERNANDES"},{"roll":"67067","name":"CHRISCIA VIOLA PEREIRA"},{"roll":"67068","name":"CHRISLY XAVIER JOAQUIM NATVIDADE FONSECA"},{"roll":"67069","name":"DIKSHA KISHOR BETKIKAR"},{"roll":"67070","name":"GAURESH KALIDAS MOPKAR"},{"roll":"67071","name":"JEMIMA JOHN M. PEREIRA"},{"roll":"67072","name":"MISELDA CRYSANNE VALENTINO MENINO FERRAO"},{"roll":"67073","name":"NEEL RAJENDRA PEDNEKAR"},{"roll":"67074","name":"PRASHANT PRAMOD MISHRA"},{"roll":"67075","name":"RICHARD GABRIEL RUI ARTUR GOMES"},{"roll":"67076","name":"RYAN SHEEL SOCORRO GREGORIO AGNELO FERNANDES"},{"roll":"67077","name":"SALIM DADAPEER GAJABEERNAVAR"},{"roll":"67078","name":"SEJAL VISHNU KELEKAR"},{"roll":"67079","name":"SHANEKA MALACHY FERNANDES"},{"roll":"67080","name":"STALAN RAUL D'SILVA"},{"roll":"67081","name":"VALENNY FEDRICA FREDDY RIBEIRO"},{"roll":"67082","name":"XANITA ISABEL SALDANHA"},{"roll":"67083","name":"YUKTA ARUN KHOLKAR"},{"roll":"67084","name":"AMAN HASSAN SHAIKH"},{"roll":"67085","name":"ANKITA NARAYAN GAWAS"},{"roll":"67086","name":"ELROY  RODRIGUES"},{"roll":"67087","name":"HABIBA BI  SHAIK"},{"roll":"67088","name":"KIMBERLY  RODRIGUES"},{"roll":"67089","name":"REGBAN ARMANDO VAZ"},{"roll":"67090","name":"RIYA RAVINDRANATH SHET VERENKAR"},{"roll":"67091","name":"SHAMMY RAJENDRA NAIK"},{"roll":"67092","name":"TANISHKA SANJAY LOTLIKAR"},{"roll":"67093","name":"VALENIE  MORAIS"},{"roll":"67094","name":"RASHWIN ROQUE FERNANDES"},{"roll":"67095","name":"KRUTIKA YADAV CHARI"},{"roll":"67096","name":"ROGER XAVIER AGUIAR"},{"roll":"67097","name":"SAMIDHA SANJIV VERENKAR"},{"roll":"67098","name":"SANTOSHI RAMDAS GAUDE"},{"roll":"67099","name":"SANYA SHAMBA SAWANT"},{"roll":"67100","name":"SHRUTIKA SURYAKANT NAIK"},{"roll":"67101","name":"GAURAV SURYAKANT RANE"},{"roll":"67102","name":"KARAN DEMANI VANI"},{"roll":"67103","name":"OM JAYJEET PARITKAR"},{"roll":"67104","name":"AAKASH ANAND GAUDE"},{"roll":"67105","name":"ABHISHEK ASHOK NAIK"},{"roll":"67106","name":"ADITI DATTATRAY DESAI"},{"roll":"67107","name":"AKASH SURYAKANT NAIK"},{"roll":"67108","name":"AMISHA ANANT GAUDE"},{"roll":"67109","name":"AMIT RAMDAS SAWANT"},{"roll":"67110","name":"ANIKET HULLO KUTTIKAR"},{"roll":"67111","name":"ANUPA PUNDALIK GAUDE"},{"roll":"67112","name":"ANUSHKA JAYAWANT HAMMANAVAR"},{"roll":"67113","name":"ASMITA ROHIDAS GAUDE"},{"roll":"67114","name":"AVINASH ANAND NAVELKAR"},{"roll":"67115","name":"BIRAJ RAMDAS GAUDE"},{"roll":"67116","name":"DATTARAM NAKUL PARAB"},{"roll":"67117","name":"DIKSHA VIRESH NAIK"},{"roll":"67118","name":"DIPTI VIVEK DESAI"},{"roll":"67119","name":"DIVYETA GAJANAN BHOMKAR"},{"roll":"67120","name":"GAURI HARI GAUDE"},{"roll":"67121","name":"HITESH JAMESH MADKAIKAR"},{"roll":"67122","name":"KAMAXI ANIL NAIK"},{"roll":"67123","name":"LAXMAN PAPANNA GAWDA"},{"roll":"67124","name":"MAHIMA KRISHNA NAVELKAR"},{"roll":"67125","name":"MALAIKA DAMODAR CHARI"},{"roll":"67126","name":"MANDESH KESHAV GAWDE"},{"roll":"67127","name":"NIHAL PRADEEP KUNKALIEKER"},{"roll":"67128","name":"OMKAR ANIL NAIK"},{"roll":"67129","name":"PREITY PRAVIN NAIK"},{"roll":"67130","name":"PUSHKAR RAJNIKANT NAIK"},{"roll":"67131","name":"RAKSHITA RAMDAS SADIYE"},{"roll":"67132","name":"RAUNAK RAJKUMAR SIRGAOKAR"},{"roll":"67133","name":"RUDRESH RAJU MADKAIKAR"},{"roll":"67134","name":"SAIKSHA PRAMOD NAIK"},{"roll":"67135","name":"SAIKSHA SHANTARAM PARAB"},{"roll":"67136","name":"SAIRAJ SHASHIKANT NAIK"},{"roll":"67137","name":"SAISH NUNO SHIRGAONKAR"},{"roll":"67138","name":"SAMIKSHA GURUDAS SHILKAR"},{"roll":"67139","name":"SANIKET SATCHIT PALKAR"},{"roll":"67140","name":"SEJAL NARENDRA MATKAR"},{"roll":"67141","name":"SHASHWAT GANESH SAWANT"},{"roll":"67142","name":"SHIVANI SHANKAR DESAI"},{"roll":"67143","name":"SHIVNATH VISHWANATH NAIK"},{"roll":"67144","name":"SHRADDHA SHEKHAR GAWDE"},{"roll":"67145","name":"SHRINIVAS /PRAVAR SIDDESH ACHARYA"},{"roll":"67146","name":"SHRUTI SHASHIKUMAR NAIK"},{"roll":"67147","name":"TANVI DILIP NAIK"},{"roll":"67148","name":"VIRAJ RAMNATH PHADTE"},{"roll":"67149","name":"YOGIRAJ THANU JAMBHAULIKAR"},{"roll":"67150","name":"DIPRAJ DILIP KORGAONKAR"},{"roll":"67151","name":"GANPAT DASHARATH SAWANT"},{"roll":"67152","name":"HRISHIKESH RAMANAND HALARNKAR"},{"roll":"67153","name":"AADARSH VISHWAS NAIK"},{"roll":"67154","name":"AARYA RAJENDRA NAIK"},{"roll":"67155","name":"AKANKSHA DINESH BANDODKAR"},{"roll":"67156","name":"AKHIL SANDEEP KAMAT"},{"roll":"67157","name":"AMRUTA RAMDAS NAIK"},{"roll":"67158","name":"ANGANA CHIMAJIRAO  ALIAS AMOL KHANVILKAR"},{"roll":"67159","name":"ANIKET GIRISH SAMANT"},{"roll":"67160","name":"DIPLAJA GAJANAN KHEDEKAR"},{"roll":"67161","name":"HARSHADA KRISHNANATH GAWDE"},{"roll":"67162","name":"KANHAIYA SADANAND SATARKAR"},{"roll":"67163","name":"NAGESH DEVIDAS NAIK"},{"roll":"67164","name":"NIDHI BHALCHANDRA NAIK"},{"roll":"67165","name":"NIHARIKA NARENDRA PARAB"},{"roll":"67166","name":"POOJA RANGANATH NAIK"},{"roll":"67167","name":"PRANAY PUNDALIK FONDEKAR"},{"roll":"67168","name":"PRATHAMESH ATMARAM NAIK"},{"roll":"67169","name":"PRATIK SANJIV SHET PARKAR"},{"roll":"67170","name":"RAINESH RAVI MALKARNEKAR"},{"roll":"67171","name":"SAMIKSHA SATISH SHENVI BORKAR"},{"roll":"67172","name":"SANIKA SAKHARAM RAUT"},{"roll":"67173","name":"SEEYA SUBHASH NAIK"},{"roll":"67174","name":"SHREYA RAJENDRA NAIK"},{"roll":"67175","name":"UTKARSHA ALIAS KANCHAN PARITOSH SAKATE"},{"roll":"67176","name":"ARCHIT VENKATESH NAYAK"},{"roll":"67177","name":"ASHVIK PRADEEP RAIKAR"},{"roll":"67178","name":"BHUSHAN SHARAD GAUDE"},{"roll":"67179","name":"DHARMESH JAYANT KAVLEKAR"},{"roll":"67180","name":"HAREESH PUNDALIK GAWADE"},{"roll":"67181","name":"HERAMBH SURENDRA NAIK"},{"roll":"67182","name":"LANJITA RAGHU GAUDE"},{"roll":"67183","name":"MANTHAN NAVNATH NAIK"},{"roll":"67184","name":"MEGHA MAHESH KADAM"},{"roll":"67185","name":"NAGESH BALU JADAV"},{"roll":"67186","name":"NIKITA MARUTI JAMBOTAKAR"},{"roll":"67187","name":"NIKITA NARESH NAIK"},{"roll":"67188","name":"RAKSHA GURU GAUDE"},{"roll":"67189","name":"SAIRAJ DEVANAND NAIK"},{"roll":"67190","name":"SAISH RAMESH NAIK"},{"roll":"67191","name":"SANAT HANUMANT MULVI"},{"roll":"67192","name":"SANIKA SHEKHAR NAIK"},{"roll":"67193","name":"SANJYOT RAMESH NAIK"},{"roll":"67194","name":"SHIVAM DAMODAR SHIRODKAR"},{"roll":"67195","name":"SHREYASH SHANKAR NAIK"},{"roll":"67196","name":"SIDHANT SANTOSH GAUDE"},{"roll":"67197","name":"SNEHA TULSHIDAS NAIK"},{"roll":"67198","name":"SOHAM SUDESH WADIKER"},{"roll":"67199","name":"SUJAY ROHIDAS GAUDE"},{"roll":"67200","name":"SWARAJ SARVODAYA NAIK MULE"},{"roll":"67201","name":"TEJAS UMESH NAIK"},{"roll":"67202","name":"VARAD RAJESH PATIL"},{"roll":"67203","name":"ANISHA VITHAL BANDEKAR"},{"roll":"67204","name":"BHUPALI PREMANAND NAIK"},{"roll":"67205","name":"DIKSHA MAHENDRA NAIK"},{"roll":"67206","name":"GANDHAR DNYANESHWAR GAWAS"},{"roll":"67207","name":"LINITA MANGESH GAWDE"},{"roll":"67208","name":"MANASI SHEKHAR BHOSALE"},{"roll":"67209","name":"NIHAL RAJENDRA KUNKOLIKAR"},{"roll":"67210","name":"PRAGATI PERU GAWDE"},{"roll":"67211","name":"PRAJAKTA PRAKASH BADAD"},{"roll":"67212","name":"RAMA EKANATH KALE"},{"roll":"67213","name":"SAPNIL SADANAND NAIK"},{"roll":"67214","name":"SHRUTVI SHAMBA PRABHUGAONKAR"},{"roll":"67215","name":"SONAM APSAR NADAF"},{"roll":"67216","name":"SURAJ MANGALDAS GAVDE"},{"roll":"67217","name":"ABHISHEK ASHOK NAIK"},{"roll":"67218","name":"ANISH SUBHASH NAIK"},{"roll":"67219","name":"MOHAMED SHEFAN MULLA"},{"roll":"67220","name":"SANA  KALAVANT"},{"roll":"67221","name":"SANKALP SANTOSH NAIK"},{"roll":"67222","name":"YUKTA VIKAS MAHALE"},{"roll":"67223","name":"HARSH  PANGHAL"},{"roll":"67224","name":"AALIYA JAVED MULLA"},{"roll":"67225","name":"ABHAY DHIRENDRA SINGH"},{"roll":"67226","name":"AFTAB SHABBIR GAFUR SAYYAD"},{"roll":"67227","name":"AKSHAY ASHOK KUMAR"},{"roll":"67228","name":"ALI  MUZAWAR"},{"roll":"67229","name":"ANIRUDDHA ANAND NAIK"},{"roll":"67230","name":"ANKIT DILIP NAIK"},{"roll":"67231","name":"ANURAG JIVAN KAMBLE"},{"roll":"67232","name":"ASHUTOSH MANOJ PHADTE"},{"roll":"67233","name":"AVIKSHIT VISHANT KURTARKAR"},{"roll":"67234","name":"AVIRAL KRIPASHANKAR PANDEY"},{"roll":"67235","name":"BHUSHANRAJ ANAND KARMALKAR"},{"roll":"67236","name":"DATTA RAJARAM MADAR"},{"roll":"67237","name":"DEVENDRA SHAMBHU PARVATKAR"},{"roll":"67238","name":"DIKSHA RATNAKAR KORGAONKAR"},{"roll":"67239","name":"DISHA JAYANTILAL KESHRANI"},{"roll":"67240","name":"FARHAT BI  "},{"roll":"67241","name":"FEMIN BABU "},{"roll":"67242","name":"GAURAAG UDAYKANT JALMI"},{"roll":"67243","name":"GAURESH SURESH MADKAIKAR"},{"roll":"67244","name":"GAUTAM MOHAN GAUDE"},{"roll":"67245","name":"GAYATRI ANTA GHADI"},{"roll":"67246","name":"HEMANGI MOHANDAS GAUDE"},{"roll":"67247","name":"JOLAN GABRIEL JOAO VAZ"},{"roll":"67248","name":"JYOTIBA NINGAPPA AMBEWADKAR"},{"roll":"67249","name":"KAVERI GAURISHANKAR GAIKWAD"},{"roll":"67250","name":"KHUSHI AJAY SINGH"},{"roll":"67251","name":"LAKHAN MOHAN HATTIKAR"},{"roll":"67252","name":"MALATI CHANDRABAHADUR SHASTRI"},{"roll":"67253","name":"MEEGAN FRANCISCO LIVRAN DIAS"},{"roll":"67254","name":"MEGHA SUNIL THORBOLE"},{"roll":"67255","name":"MOHSIN AKBAR SHAIKH"},{"roll":"67256","name":"MUZNA SHOUKAT SHAIKH"},{"roll":"67257","name":"NEHA NARESH KUBAL"},{"roll":"67258","name":"NIKHIL MARUTHI NARVEKAR"},{"roll":"67259","name":"NIKHITA BASAVARAJ KAMMAR"},{"roll":"67260","name":"OMKAR RAMDAS VAIGANKAR"},{"roll":"67261","name":"PINAL BHARAT PATEL"},{"roll":"67262","name":"PRACHI SAJU WADKAR"},{"roll":"67263","name":"PRALAY PANDHARI GAONKAR"},{"roll":"67264","name":"PRANAY DNYANESHWAR NAIK"},{"roll":"67265","name":"PRANAY PANDURANG GAUDE"},{"roll":"67266","name":"PRASAD UMESH HARLE"},{"roll":"67267","name":"PRASANNA DINESH TALEKAR"},{"roll":"67268","name":"PRATHAMESH KRISHNA GHADI"},{"roll":"67269","name":"PRERANA PRAMOD NAIK"},{"roll":"67270","name":"PRERNA PREMANAND TURI"},{"roll":"67271","name":"PRERNA RAMESH GHADI"},{"roll":"67272","name":"PRITIKUMARI DHARMENDRA GUPTA"},{"roll":"67273","name":"RAVISH NARAYAN BHAGAT"},{"roll":"67274","name":"REESHAD DAMODAR GAUDE"},{"roll":"67275","name":"ROHAN RAJENDRA DIWADKAR"},{"roll":"67276","name":"ROHIDAS PRAVEEN KRISHNA BORKAR"},{"roll":"67277","name":"RONAK LAXMIKANT NAIK GAONKAR"},{"roll":"67278","name":"RUTIKESH SURESH KUNDAIKAR"},{"roll":"67279","name":"RUTUJA DILIP CHARI"},{"roll":"67280","name":"SACHI SANDIP NAIK"},{"roll":"67281","name":"SACHIL TULSIDAS NAIK"},{"roll":"67282","name":"SADIK AHAMAD  RATTIHALLI"},{"roll":"67283","name":"SAGAR GOPAL GAWDE"},{"roll":"67284","name":"SAILI VISHNU GAUDE"},{"roll":"67285","name":"SALIL SUDAS SAWANT"},{"roll":"67286","name":"SAMARIN MAHABOOB MULLA"},{"roll":"67287","name":"SANTOSH BABEL MOTESH SOUZ"},{"roll":"67288","name":"SAVANI GURUDAS NAIK"},{"roll":"67289","name":"SELWYN ROCKY ANDRADE"},{"roll":"67290","name":"SEPHERA MARCELLA  ZORAIDA DE MATOS SEQUEIRA"},{"roll":"67291","name":"SHAHUB KUMAR BIPIN SHAH"},{"roll":"67292","name":"SHREYASH SHEKHAR KANKONKAR"},{"roll":"67293","name":"SMINIL SUNIL KUMAR N.S."},{"roll":"67294","name":"SMITESH SITARAM SAWANT"},{"roll":"67295","name":"STEVEN MATHIAS MENEZES"},{"roll":"67296","name":"TANVESH GOVIND MADKAIKAR GAUDE"},{"roll":"67297","name":"TASMIYA MEHABOOB JANGI"},{"roll":"67298","name":"VARUN DEVRAI GURAV KERKAR"},{"roll":"67299","name":"VEDANT RAJENDRA NAIK"},{"roll":"67300","name":"VINAYAK SIVADAS M."},{"roll":"67301","name":"VIVEK RAVINDRA YADAV"},{"roll":"67302","name":"YASH SANJAY FATARPEKAR"},{"roll":"67303","name":"YASH SHASHIKANT FADATE GAONKAR"},{"roll":"67304","name":"YOGITA CHITRASEN GUPTA"},{"roll":"67305","name":"YOGITA YESHWANT GHADI"},{"roll":"67306","name":"YUGA NARENDRA NAIK"},{"roll":"67307","name":"YUVRAJ PANDURANG GAUDE"},{"roll":"67308","name":"GITESH DEU GAWDE"},{"roll":"67309","name":"PRATHAMESH NARAYAN SAWANT"},{"roll":"67310","name":"ABEL  ABRAHAM"},{"roll":"67311","name":"ABHISHEK V. R. "},{"roll":"67312","name":"ADITYA RAGHUVIR GAWADE"},{"roll":"67313","name":"AKSHATA ASHOK KALGUTKAR"},{"roll":"67314","name":"BILAL RASUL NADAF"},{"roll":"67315","name":"CHANCHAL SHERSING SHEORAN"},{"roll":"67316","name":"DHANYA RAMAKRISHNA BHAT"},{"roll":"67317","name":"GEETESH GANPAT KAWALEKAR"},{"roll":"67318","name":"HASSAN  ALI ISLAMUDDIN KHAN"},{"roll":"67319","name":"HERAMB HEMANT SAWANT"},{"roll":"67320","name":"KAVITA PARASAPPA BARGI"},{"roll":"67321","name":"KHUSHI  SHARMA"},{"roll":"67322","name":"KUNAL GOKARNA SHARMA"},{"roll":"67323","name":"MEGHNA KIRAN VERENKAR"},{"roll":"67324","name":"MOBI BIJU "},{"roll":"67325","name":"MOHIEBA BI  MULLAM"},{"roll":"67326","name":"PRADNYA PAWAN NATEKAR"},{"roll":"67327","name":"PRAPTI PRATAP SAWANT"},{"roll":"67328","name":"PREETI SHRIKANT INCHAL"},{"roll":"67329","name":"RAJANI  KUMARI"},{"roll":"67330","name":"RAMCHANDRA GIRISH WADIKAR"},{"roll":"67331","name":"RITIKA ROHIT TEWARI"},{"roll":"67332","name":"ROHAN BHARAT PATEL"},{"roll":"67333","name":"ROHAN PRAKASH GAUDE"},{"roll":"67334","name":"ROHITKUMAR JAVTARAM MALVIYA"},{"roll":"67335","name":"SAGAR BHIMPRASAD GOND"},{"roll":"67336","name":"SAURABH AMARNATH JHA"},{"roll":"67337","name":"SHACHI MAHESH GANPULE"},{"roll":"67338","name":"SHARADA MANTESH KURI"},{"roll":"67339","name":"SHITIJA SHAMSUNDAR SAMANT"},{"roll":"67340","name":"SHIVAM RAMESH GAWAS"},{"roll":"67341","name":"SIDHESH GAJANAN TELI"},{"roll":"67342","name":"SIMRAN RAJENDRA NAIK"},{"roll":"67343","name":"SNEHA  JHA"},{"roll":"67344","name":"SOHA BI  "},{"roll":"67345","name":"SWEEDAL RENISHA MATHIAS"},{"roll":"67346","name":"VED ANIL PAIGUINKAR"},{"roll":"67347","name":"VIVEK KUMAR SINGH"},{"roll":"67348","name":"VIVEK V. NAYAK"},{"roll":"67349","name":"VRUDHI VIKAS BHANDANKAR"},{"roll":"67350","name":"YASMIN  SAYED"},{"roll":"67351","name":"YOGENDAR  SINGH"},{"roll":"67352","name":"ANASVI ANIL NAIK"},{"roll":"67353","name":"ASTON  GOIS"},{"roll":"67354","name":"CHETANA CHANDRAKANT NAIK"},{"roll":"67355","name":"CHINMAY SHRIKANT NAIK"},{"roll":"67356","name":"GAUTAM RATNAKER NAIK"},{"roll":"67357","name":"JATIN JIVAJI SHENVI VARDE BORKER"},{"roll":"67358","name":"KRISHNAVARDHAN NAVANATH SAWANT"},{"roll":"67359","name":"MAHEEMA BHAGWANSING RAJPUROHIT"},{"roll":"67360","name":"MENAKA RAGHUNATH BISHNOI"},{"roll":"67361","name":"NAGUESH SANDESH BANDODKAR"},{"roll":"67362","name":"NAKUL PANDURANG GAUDE"},{"roll":"67363","name":"NAVEENKUMAR  J.P"},{"roll":"67364","name":"PANKAJGIRI KISHORGIRI GOSWAMI"},{"roll":"67365","name":"PRACHI PREMANAND NAIK"},{"roll":"67366","name":"PRASIDHI EKNATH KANKONKAR"},{"roll":"67367","name":"SAHIL SURESH NAIK"},{"roll":"67368","name":"SAILY TUKARAM NAIK"},{"roll":"67369","name":"SAJIT SUDHARMAN "},{"roll":"67370","name":"SHIVAM SAMPURNANAND RANE"},{"roll":"67371","name":"SHREEYASH SATYAVAN NAIK"},{"roll":"67372","name":"SIYA SURYAKANT GAONKAR"},{"roll":"67373","name":"ALINA MARY JOSEPH"},{"roll":"67374","name":"AVEESHA KANTA GAUDE"},{"roll":"67375","name":"AYMAN RAHMATULLAH KHAN"},{"roll":"67376","name":"CHETAN SURYAJI KAKODKAR"},{"roll":"67377","name":"DEERAJ MAHESH NAIK"},{"roll":"67378","name":"DIKSHA PREMANAND NAIK"},{"roll":"67379","name":"FALAK CASSIM SHAH"},{"roll":"67380","name":"HARSHADA TULSHIDAS GAUDE"},{"roll":"67381","name":"HASSAN MULLA "},{"roll":"67382","name":"KAMLESH JOGARAM RATHOD"},{"roll":"67383","name":"NAEEM ABDULSAB BETGERI"},{"roll":"67384","name":"NEHA NILESH NAIK"},{"roll":"67385","name":"PARAM RATNAKAR GAUDE"},{"roll":"67386","name":"PRANALI MANOHAR DHULAPKAR"},{"roll":"67387","name":"PURVA RAMA NAIK"},{"roll":"67388","name":"RAJ SHYAM KARMALKAR"},{"roll":"67389","name":"RITISHA SURESH SHENOY SANGAONKAR"},{"roll":"67390","name":"SALMAN ILAHI NADAF"},{"roll":"67391","name":"SAMA SALIM SHAH"},{"roll":"67392","name":"SEEYA SANDEEP NAIK"},{"roll":"67393","name":"SIYA ULHAS NAIK"},{"roll":"67394","name":"TOUFIQ SAMIULLHA KHAN"},{"roll":"67395","name":"VIKAS ARUNKUMAR SHARMA"},{"roll":"67396","name":"VISHAL RATHOD "},{"roll":"67397","name":"SATWIK SHRIKUMAR SARJYOTISHI"},{"roll":"67398","name":"ANEESH SURESH SADHALE"},{"roll":"67399","name":"ANISHA DEVIDAS KUNKALIKAR"},{"roll":"67400","name":"ARYAN  DUTTA"},{"roll":"67401","name":"ATHARVA RAJESH SINAI TALAULIKAR"},{"roll":"67402","name":"ESHA RAGHURAJ GHATE"},{"roll":"67403","name":"GAURAKSH BABULI GAUDE"},{"roll":"67404","name":"HRITHIKA ABHIT PRABHU VELGUENKAR"},{"roll":"67405","name":"LOKAAMBIKA  TIRUKKOVALLURI"},{"roll":"67406","name":"OMKAR MANJUNATH HEGDE"},{"roll":"67407","name":"PRANJAL  DOKI"},{"roll":"67408","name":"ROHIT  NAYAK B."},{"roll":"67409","name":"SHRIGANESH NITYANAND BHAT"},{"roll":"67410","name":"SUPREET MAHESH SINAI SALELKAR"},{"roll":"67411","name":"SUPRIYA  PIDUGU"},{"roll":"67412","name":"T. VINIT RAMESH PAI"},{"roll":"67413","name":"SHARV GANADISH BICHE"},{"roll":"67414","name":"JOSHUA  D'SILVA"},{"roll":"67415","name":"PUNIT PANDURANG NAIK"},{"roll":"67416","name":"SARVEDNYA SURENDRA DANGUI"},{"roll":"67417","name":"TANISHA G. NAIK"},{"roll":"67418","name":"VEDANG VASUDEV NAIK"},{"roll":"67419","name":"MELIZA VELIMA GOMES"},{"roll":"67420","name":"AMBICA ANAND GAUDE"},{"roll":"67421","name":"GAJANAN FONDU GHADI"},{"roll":"67422","name":"GURUDAS MASHNU TAMBULKAR"},{"roll":"67423","name":"SHRUTIKA RAMESH TAWADE"},{"roll":"67424","name":"SIDDHANT KAMALKUMAR KAVLEKAR"},{"roll":"67425","name":"SIDDHARTH JAGADISH GAWDE"},{"roll":"67426","name":"NIKHAT FATIMA  "},{"roll":"67427","name":"PRASAD MANOHAR DATEKAR"},{"roll":"67428","name":"SUJAY SURYA MADKAIKAR"},{"roll":"67429","name":"SONALI SANDESH NAIK"},{"roll":"67430","name":"DIPESH DINESH NAIK"}]